code_recap/__init__.py
code_recap/arguments.py
code_recap/cli.py
code_recap/deploy_reports.py
code_recap/formatting.py
code_recap/generate_blog_post.py
code_recap/generate_html_report.py
code_recap/git_activity_review.py
code_recap/git_utils.py
code_recap/list_commits_by_date.py
code_recap/paths.py
code_recap/summarize_activity.py
code_recap/summarize_daily_activity.py
code_recap-1.3.1.dist-info/METADATA
code_recap-1.3.1.dist-info/WHEEL
code_recap-1.3.1.dist-info/entry_points.txt
code_recap-1.3.1.dist-info/licenses/LICENSE
code_recap-1.3.1.dist-info/RECORD
