Metadata-Version: 2.4
Name: code-recap
Version: 1.3.1
Summary: Git activity analysis and LLM-powered summary tools for developers and consultants
Project-URL: Homepage, https://github.com/nrb-tech/code-recap
Project-URL: Repository, https://github.com/nrb-tech/code-recap
Project-URL: Documentation, https://github.com/nrb-tech/code-recap#readme
Project-URL: Issues, https://github.com/nrb-tech/code-recap/issues
Author: Code Recap Contributors
License-Expression: MIT
License-File: LICENSE
Keywords: activity,consulting,git,llm,productivity,reporting,summary
Classifier: Development Status :: 4 - Beta
Classifier: Environment :: Console
Classifier: Intended Audience :: Developers
Classifier: License :: OSI Approved :: MIT License
Classifier: Operating System :: OS Independent
Classifier: Programming Language :: Python :: 3
Classifier: Programming Language :: Python :: 3.9
Classifier: Programming Language :: Python :: 3.10
Classifier: Programming Language :: Python :: 3.11
Classifier: Programming Language :: Python :: 3.12
Classifier: Programming Language :: Python :: 3.13
Classifier: Topic :: Software Development
Classifier: Topic :: Software Development :: Version Control :: Git
Classifier: Topic :: Utilities
Requires-Python: >=3.9
Requires-Dist: litellm>=1.55.0
Requires-Dist: pyyaml>=6.0
Provides-Extra: dev
Requires-Dist: build>=1.0.0; extra == 'dev'
Requires-Dist: pre-commit>=4.0.0; extra == 'dev'
Requires-Dist: ruff>=0.8.0; extra == 'dev'
Requires-Dist: twine>=5.0.0; extra == 'dev'
